vid-prepper/augmentor.py
vid-prepper/detector.py
vid-prepper/loader.py
vid-prepper/metadata.py
vid-prepper/standardize.py
vid_prepper/augmentor.py
vid_prepper/detector.py
vid_prepper/loader.py
vid_prepper/metadata.py
vid_prepper/standardize.py
vid_prepper-0.1.2.dist-info/licenses/LICENSE
vid_prepper-0.1.2.dist-info/METADATA
vid_prepper-0.1.2.dist-info/WHEEL
vid_prepper-0.1.2.dist-info/entry_points.txt
vid_prepper-0.1.2.dist-info/top_level.txt
vid_prepper-0.1.2.dist-info/RECORD
