Metadata-Version: 2.4
Name: vid-prepper
Version: 0.1.2
Summary: Package for preparing videos for deep learning models
Author-email: Jamie Petherbridge-Conroy <jamie@jamiepc.com>
License-Expression: Apache-2.0
Classifier: Programming Language :: Python :: 3
Classifier: Operating System :: OS Independent
Requires-Python: >=3.10
License-File: LICENSE
Requires-Dist: torch<3.0.0,>=2.0.0
Requires-Dist: torchvision<1.0.0,>=0.17.0
Requires-Dist: transformers<5.0.0,>=4.40.0
Requires-Dist: numpy<2.0.0,>=1.21.0
Requires-Dist: scenedetect<1.0.0,>=0.6.0
Requires-Dist: kornia<1.0.0,>=0.7.0
Requires-Dist: webdataset<1.0.0,>=0.2.0
Requires-Dist: opencv-python<5.0.0,>=4.5.0
Requires-Dist: av>=15.1.0
Provides-Extra: gpu
Requires-Dist: torch[cuda]<3.0.0,>=2.0.0; extra == "gpu"
Provides-Extra: video
Requires-Dist: av<16.0.0,>=15.0.0; extra == "video"
Provides-Extra: dev
Requires-Dist: pytest>=7.0.0; extra == "dev"
Requires-Dist: pytest-cov>=4.0.0; extra == "dev"
Requires-Dist: black>=23.0.0; extra == "dev"
Requires-Dist: flake8>=6.0.0; extra == "dev"
Requires-Dist: mypy>=1.0.0; extra == "dev"
Requires-Dist: pre-commit>=3.0.0; extra == "dev"
Dynamic: license-file
